gptplot/__init__.py
gptplot/analyzer.py
gptplot/cli.py
gptplot/config_loader.py
gptplot/formatting.py
gptplot/interactive.py
gptplot/io_handler.py
gptplot/plotter_2d.py
gptplot/plotter_3d.py
gptplot/styles.py
gptplot/utils.py
gptplot-0.1.4.dist-info/licenses/LICENSE
gptplot-0.1.4.dist-info/METADATA
gptplot-0.1.4.dist-info/WHEEL
gptplot-0.1.4.dist-info/entry_points.txt
gptplot-0.1.4.dist-info/top_level.txt
gptplot-0.1.4.dist-info/RECORD
